app/__init__.py
sistema_bancario-0.0.1.dist-info/METADATA
sistema_bancario-0.0.1.dist-info/WHEEL
sistema_bancario-0.0.1.dist-info/top_level.txt
sistema_bancario-0.0.1.dist-info/RECORD
