Metadata-Version: 2.1
Name: sistema-bancario
Version: 0.0.1
Summary: Meu sistema Bancario
Home-page: https://github.com/MarcusViniciusBarcelos/sistema_bancario
Author: Marcus Vinicius Barcelos
Author-email: marcusbarcelos2001@gmail.com
License: UNKNOWN
Platform: UNKNOWN
Requires-Python: >=3.8
